[
    {
        "key": "group_62300bdb7aa3c",
        "title": "Edje Widget - My Account",
        "fields": [
            {
                "key": "field_62300c098d013",
                "label": "Label",
                "name": "label",
                "type": "text",
                "instructions": "",
                "required": 0,
                "conditional_logic": 0,
                "wrapper": {
                    "width": "",
                    "class": "",
                    "id": ""
                },
                "default_value": "Login",
                "placeholder": "",
                "prepend": "",
                "append": "",
                "maxlength": ""
            },
            {
                "key": "field_62300bef8d012",
                "label": "Label Logged-in",
                "name": "label_logged_in",
                "type": "text",
                "instructions": "",
                "required": 0,
                "conditional_logic": 0,
                "wrapper": {
                    "width": "",
                    "class": "",
                    "id": ""
                },
                "default_value": "My Account",
                "placeholder": "",
                "prepend": "",
                "append": "",
                "maxlength": ""
            }
        ],
        "location": [
            [
                {
                    "param": "widget",
                    "operator": "==",
                    "value": "h_myaccount"
                }
            ]
        ],
        "menu_order": 0,
        "position": "normal",
        "style": "default",
        "label_placement": "top",
        "instruction_placement": "label",
        "hide_on_screen": "",
        "active": true,
        "description": "",
        "show_in_rest": 0
    }
]